qiskit_tensorflow/__init__.py
qiskit_tensorflow-0.0.1.dist-info/LICENSE
qiskit_tensorflow-0.0.1.dist-info/METADATA
qiskit_tensorflow-0.0.1.dist-info/WHEEL
qiskit_tensorflow-0.0.1.dist-info/top_level.txt
qiskit_tensorflow-0.0.1.dist-info/RECORD
